ipanema/__init__.py
ipanema/confidence/__init__.py
ipanema/confidence/intervals.py
ipanema/confidence/propagator.py
ipanema/core/__init__.py
ipanema/core/device.py
ipanema/core/host.py
ipanema/core/multi_par.py
ipanema/core/python.py
ipanema/core/types.py
ipanema/core/utils.py
ipanema/interpolate/__init__.py
ipanema/interpolate/interpolation.py
ipanema/optimizers/__init__.py
ipanema/optimizers/optimizers.py
ipanema/params/__init__.py
ipanema/params/blinding.py
ipanema/params/parameter.py
ipanema/sample/__init__.py
ipanema/sample/samples.py
ipanema/splot/__init__.py
ipanema/splot/sweights.py
ipanema/src/ipanema/test_ipatia.py
ipanema/tools/__init__.py
ipanema/tools/misc.py
ipanema/tools/uncertainties_wrapper.py
ipanema/utils/__init__.py
ipanema/utils/print_reports.py
ipanema3-1.0.6.dist-info/LICENSE
ipanema3-1.0.6.dist-info/METADATA
ipanema3-1.0.6.dist-info/WHEEL
ipanema3-1.0.6.dist-info/top_level.txt
ipanema3-1.0.6.dist-info/RECORD
