Metadata-Version: 2.1
Name: ipanema3
Version: 1.0.6
Summary: Fitting Tool for High Energy Physics
Home-page: https://github.com/marromlam/ipanema.git
Download-URL: https://github.com/marromlam/ipanema.git
Author: Marcos Romero Lamas
Author-email: mromerol@cern.ch
License: GNU AFFERO GENERAL PUBLIC LICENSE
Keywords: curve-fitting,optimization,hyperthreading
Platform: Linux
Platform: macOS
Platform: Windows
Requires-Python: >=3.7
License-File: LICENSE
Requires-Dist: asteval (>=0.9.12)
Requires-Dist: numpy (>=1.10)
Requires-Dist: scipy (>=0.19)
Requires-Dist: six (>1.10)
Requires-Dist: uncertainties (>=3.0)
Requires-Dist: pandas
Requires-Dist: numdifftools
Requires-Dist: emcee (>=3.0)
Requires-Dist: uproot3
Requires-Dist: hjson
Requires-Dist: reikna
Requires-Dist: iminuit (==1.5.2)
Requires-Dist: matplotlib
Requires-Dist: tqdm
Requires-Dist: corner
Requires-Dist: complot
Requires-Dist: lib99ocl
Requires-Dist: pyopencl
